nats_object/__init__.py
nats_object-0.0.0.dist-info/licenses/LICENSE
nats_object-0.0.0.dist-info/METADATA
nats_object-0.0.0.dist-info/WHEEL
nats_object-0.0.0.dist-info/top_level.txt
nats_object-0.0.0.dist-info/RECORD
