Metadata-Version: 2.4
Name: nats-object
Version: 0.0.0
Summary: NATS Object Store functionality - package name reserved
Author-email: Casper Beyer <casper@synadia.com>
Project-URL: Homepage, https://github.com/nats-io/nats.py
Classifier: Programming Language :: Python :: 3
Classifier: License :: OSI Approved :: MIT License
Classifier: Operating System :: OS Independent
Requires-Python: >=3.8
License-File: LICENSE
Dynamic: license-file
